LICENSE
name2user/__init__.py
name2user/name2user.py
name2user/user_name_creation_methods.py
name2user/user_name_generator.py
name2user-1.0.0.dist-info/LICENSE
name2user-1.0.0.dist-info/METADATA
name2user-1.0.0.dist-info/WHEEL
name2user-1.0.0.dist-info/entry_points.txt
name2user-1.0.0.dist-info/RECORD
