Metadata-Version: 2.1
Name: name2user
Version: 1.0.0
Summary: A tool to generate user names from one or a list of full names.
Home-page: https://github.com/b4d-ra1c4u/name2user
License: WTFPL
Keywords: generator,pentesting,hacking
Author: b4d_ra1c4u
Author-email: b4d_ra1c4u@proton.me
Requires-Python: >=3.7,<4.0
Classifier: Environment :: Console
Classifier: License :: Other/Proprietary License
Classifier: Programming Language :: Python :: 3
Classifier: Programming Language :: Python :: 3.7
Classifier: Programming Language :: Python :: 3.8
Classifier: Programming Language :: Python :: 3.9
Classifier: Programming Language :: Python :: 3.10
Classifier: Programming Language :: Python :: 3.11
Classifier: Programming Language :: Python :: 3
Classifier: Topic :: Software Development :: Testing
Project-URL: Repository, https://github.com/b4d-ra1c4u/name2user
